pepperize_cdk_serverless_cluster_from_snapshot/__init__.py
pepperize_cdk_serverless_cluster_from_snapshot/py.typed
pepperize_cdk_serverless_cluster_from_snapshot/_jsii/__init__.py
pepperize_cdk_serverless_cluster_from_snapshot/_jsii/cdk-serverless-cluster-from-snapshot@0.0.803.jsii.tgz
pepperize.cdk_serverless_cluster_from_snapshot-0.0.803.dist-info/LICENSE
pepperize.cdk_serverless_cluster_from_snapshot-0.0.803.dist-info/METADATA
pepperize.cdk_serverless_cluster_from_snapshot-0.0.803.dist-info/WHEEL
pepperize.cdk_serverless_cluster_from_snapshot-0.0.803.dist-info/top_level.txt
pepperize.cdk_serverless_cluster_from_snapshot-0.0.803.dist-info/RECORD
