Metadata-Version: 2.1
Name: pepperize.cdk-serverless-cluster-from-snapshot
Version: 0.0.803
Summary: Deprecated: Use https://docs.aws.amazon.com/cdk/api/v2/docs/aws-cdk-lib.aws_rds.ServerlessClusterFromSnapshot.html
Home-page: https://github.com/pepperize/cdk-serverless-cluster-from-snapshot.git
Author: Patrick Florek<patrick.florek@gmail.com>
License: MIT
Project-URL: Source, https://github.com/pepperize/cdk-serverless-cluster-from-snapshot.git
Classifier: Intended Audience :: Developers
Classifier: Operating System :: OS Independent
Classifier: Programming Language :: JavaScript
Classifier: Programming Language :: Python :: 3 :: Only
Classifier: Programming Language :: Python :: 3.8
Classifier: Programming Language :: Python :: 3.9
Classifier: Programming Language :: Python :: 3.10
Classifier: Programming Language :: Python :: 3.11
Classifier: Typing :: Typed
Classifier: Development Status :: 7 - Inactive
Classifier: License :: OSI Approved
Requires-Python: ~=3.8
License-File: LICENSE
Requires-Dist: aws-cdk-lib <3.0.0,>=2.8.0
Requires-Dist: constructs <11.0.0,>=10.0.5
Requires-Dist: jsii <2.0.0,>=1.93.0
Requires-Dist: publication >=0.0.3
Requires-Dist: typeguard ~=2.13.3
